CHANGES.txt
MANIFEST.in
README.txt
setup.cfg
setup.py
js/__init__.py
js.backbone.egg-info/PKG-INFO
js.backbone.egg-info/SOURCES.txt
js.backbone.egg-info/dependency_links.txt
js.backbone.egg-info/entry_points.txt
js.backbone.egg-info/namespace_packages.txt
js.backbone.egg-info/not-zip-safe
js.backbone.egg-info/requires.txt
js.backbone.egg-info/top_level.txt
js/backbone/__init__.py
js/backbone/test_backbone.js.txt
js/backbone/resources/backbone-min.js
js/backbone/resources/backbone.js