Metadata-Version: 1.0
Name: js.backbone
Version: 1.0.0
Summary: Fanstatic packaging of backbone.js
Home-page: https://github.com/podhmo/js.backbone
Author: podhmo podhmo
Author-email: podhmo@example.jp
License: BSD
Platform: UNKNOWN
